drapixcol/__init__.py
drapixcol-1.2.dist-info/LICENSE.txt
drapixcol-1.2.dist-info/METADATA
drapixcol-1.2.dist-info/WHEEL
drapixcol-1.2.dist-info/top_level.txt
drapixcol-1.2.dist-info/RECORD
