Metadata-Version: 2.1
Name: drapixcol
Version: 1.2
Summary: Python library for drawing with pixels.
Home-page: https://github.com/lina-torovoltas/Drapixcol
Author: Lina_Torovoltas
Keywords: python color colors paint drapixcol pixel drawing
Classifier: Programming Language :: Python :: 3.9
Classifier: License :: OSI Approved :: MIT License
Classifier: Operating System :: OS Independent
Requires-Python: >=3.9
License-File: LICENSE.txt
Requires-Dist: requests >=2.25.1
Requires-Dist: pillow >=10.1.0
Requires-Dist: opencv-python >=4.8.1.78
Requires-Dist: numpy >=1.26.2
